{
    "editor.fontFamily": "Source Code Pro, Menlo, Monaco, 'Courier New', monospace",
    "editor.fontSize": 14,
    "editor.formatOnPaste": true,
    "editor.rulers": [80],
    "editor.tabSize": 2,
    "emmet.triggerExpansionOnTab": true,
    "files.exclude": {
        "__pycache__": true
    },
    "files.insertFinalNewline": true,
    "files.trimTrailingWhitespace": true,
    "terminal.integrated.confirmOnExit": true,
    "workbench.colorTheme": "Monokai",
    "workbench.iconTheme": "vs-seti"
}
